MANIFEST.in
README.rst
rabbitmq_munin.py
setup.py
rabbitmq_munin.egg-info/PKG-INFO
rabbitmq_munin.egg-info/SOURCES.txt
rabbitmq_munin.egg-info/dependency_links.txt
rabbitmq_munin.egg-info/entry_points.txt
rabbitmq_munin.egg-info/requires.txt
rabbitmq_munin.egg-info/top_level.txt