Metadata-Version: 1.1
Name: rabbitmq-munin
Version: 0.2
Summary: A munin plugin to monitor rabbitmq queues.
Home-page: https://github.com/freyes/rabbitmq_munin
Author: Felipe Reyes
Author-email: freyes@tty.cl
License: BSD
Keywords: rabbitmq munin plugin
Platform: UNKNOWN
Classifier: Development Status :: 3 - Alpha
Classifier: Topic :: Utilities
Classifier: License :: OSI Approved :: BSD License
Classifier: Environment :: Plugins
Classifier: Intended Audience :: System Administrators
Classifier: Programming Language :: Python :: 2
Classifier: Programming Language :: Python :: 2.4
Classifier: Programming Language :: Python :: 2.5
Classifier: Programming Language :: Python :: 2.6
Classifier: Programming Language :: Python :: 2.7
Classifier: Topic :: System :: Monitoring
